connectorx-0.4.5.dist-info/METADATA
connectorx-0.4.5.dist-info/WHEEL
connectorx-0.4.5.dist-info/license_files/LICENSE
connectorx/connectorx.pyi
connectorx/py.typed
connectorx/tests/benchmarks.py
connectorx/tests/conftest.py
connectorx/tests/test_arrow.py
connectorx/tests/test_bigquery.py
connectorx/tests/test_clickhouse.py
connectorx/tests/test_dask.py
connectorx/tests/test_federation.py
connectorx/tests/test_meta.py
connectorx/tests/test_modin.py
connectorx/tests/test_mssql.py
connectorx/tests/test_mysql.py
connectorx/tests/test_oracle.py
connectorx/tests/test_partition.py
connectorx/tests/test_polars.py
connectorx/tests/test_postgres.py
connectorx/tests/test_redshift.py
connectorx/tests/test_sqlite.py
connectorx/tests/test_trino.py
connectorx/tests/__init__.py
connectorx/__init__.py
LICENSE
connectorx/connectorx.cp313-win_amd64.pyd
connectorx-0.4.5.dist-info/RECORD
