Metadata-Version: 2.1
Name: connectorx
Version: 0.4.5
License-File: LICENSE
Author: Weiyuan Wu <youngw@sfu.ca>
Author-email: Weiyuan Wu <youngw@sfu.ca>
License: MIT
Requires-Python: >=3.10
Project-URL: Issues, https://github.com/sfu-db/connector-x/issues
Project-URL: Documentation, https://sfu-db.github.io/connector-x/intro.html
Project-URL: Homepage, https://github.com/sfu-db/connector-x
Project-URL: Repository, https://github.com/sfu-db/connector-x
